{"error_code":0,"session_token":"940164b4-027c-4746-ab0f-6ea779635519","md_get_history_response":{"trades":[{"date":"2019-12-30","bid":291.6,"ask":291.7,"last":291.52,"open":289.46,"high":292.69,"low":285.22,"volume":30144771.0,"turnover":8735629255.995001,"feed":15,"ticker":"AAPL","num_trades":245510},{"date":"2019-12-27","bid":289.95,"ask":290.0,"last":289.8,"open":291.12,"high":293.97,"low":288.12,"volume":30779764.0,"turnover":8952579765.651501,"feed":15,"ticker":"AAPL","num_trades":245681},{"date":"2019-12-26","bid":290.82,"ask":290.85,"last":289.91,"open":284.82,"high":289.98,"low":284.7,"volume":20408853.0,"turnover":5877519855.6148,"feed":15,"ticker":"AAPL","num_trades":164279},{"date":"2019-12-24","bid":284.31,"ask":284.43,"last":284.27,"open":284.69,"high":284.89,"low":282.9197,"volume":10057292.0,"turnover":2856805269.8807,"feed":15,"ticker":"AAPL","num_trades":81831},{"date":"2019-12-23","bid":284.5,"ask":284.56,"last":284.0,"open":280.53,"high":284.25,"low":280.48,"volume":20681752.0,"turnover":5854274821.3996,"feed":15,"ticker":"AAPL","num_trades":164780},{"date":"2019-12-20","bid":279.32,"ask":279.5,"last":279.44,"open":282.23,"high":282.65,"low":278.56,"volume":45398440.0,"turnover":12307635632.794001,"feed":15,"ticker":"AAPL","num_trades":200428},{"date":"2019-12-19","bid":280.2,"ask":280.3,"last":280.02,"open":279.5,"high":281.18,"low":278.95,"volume":19328647.0,"turnover":5409665772.8973,"feed":15,"ticker":"AAPL","num_trades":153639},{"date":"2019-12-18","bid":279.98,"ask":280.05,"last":279.74,"open":279.68,"high":281.9,"low":279.12,"volume":23194785.0,"turnover":6501925472.5124,"feed":15,"ticker":"AAPL","num_trades":169774},{"date":"2019-12-17","bid":280.32,"ask":280.35,"last":280.41,"open":279.82,"high":281.77,"low":278.8,"volume":24858951.0,"turnover":6976452006.5823,"feed":15,"ticker":"AAPL","num_trades":188257},{"date":"2019-12-16","bid":280.25,"ask":280.3,"last":279.86,"open":277.0,"high":280.79,"low":276.98,"volume":29170417.0,"turnover":7677748794.9539,"feed":15,"ticker":"AAPL","num_trades":195308},{"date":"2019-12-13","bid":275.26,"ask":275.33,"last":275.15,"open":271.46,"high":275.3,"low":270.93,"volume":28538164.0,"turnover":7815073431.5072,"feed":15,"ticker":"AAPL","num_trades":234517},{"date":"2019-12-12","bid":272.95,"ask":272.99,"last":271.46,"open":267.75,"high":272.5599,"low":267.321,"volume":28231163.0,"turnover":7627462948.7133,"feed":15,"ticker":"AAPL","num_trades":232726},{"date":"2019-12-11","bid":270.85,"ask":271.05,"last":270.77,"open":268.81,"high":271.1,"low":268.5,"volume":17669955.0,"turnover":4774670505.492,"feed":15,"ticker":"AAPL","num_trades":135702},{"date":"2019-12-10","bid":268.4,"ask":268.5,"last":268.48,"open":268.6,"high":270.07,"low":265.86,"volume":20206470.0,"turnover":5428239570.1436,"feed":15,"ticker":"AAPL","num_trades":173828},{"date":"2019-12-09","bid":266.8,"ask":266.88,"last":266.92,"open":269.96,"high":270.8,"low":264.91,"volume":29364877.0,"turnover":6709826223.0263,"feed":15,"ticker":"AAPL","num_trades":199189},{"date":"2019-12-06","bid":270.55,"ask":270.61,"last":270.71,"open":267.52,"high":271.0,"low":267.3,"volume":22841872.0,"turnover":6162165908.1702,"feed":15,"ticker":"AAPL","num_trades":184078},{"date":"2019-12-05","bid":265.94,"ask":265.99,"last":265.58,"open":263.79,"high":265.89,"low":262.73,"volume":16130043.0,"turnover":4266470964.5014,"feed":15,"ticker":"AAPL","num_trades":137892},{"date":"2019-12-04","bid":261.41,"ask":261.5,"last":261.74,"open":261.07,"high":263.31,"low":260.68,"volume":14917723.0,"turnover":3909220805.0478,"feed":15,"ticker":"AAPL","num_trades":138451},{"date":"2019-12-03","bid":258.93,"ask":259.09,"last":259.45,"open":258.31,"high":259.53,"low":256.29,"volume":23599700.0,"turnover":6088753823.4938,"feed":15,"ticker":"AAPL","num_trades":223274},{"date":"2019-12-02","bid":263.6,"ask":263.82,"last":264.16,"open":267.27,"high":268.25,"low":263.45,"volume":19291651.0,"turnover":5116006164.0096,"feed":15,"ticker":"AAPL","num_trades":153457},{"date":"2019-11-29","bid":267.35,"ask":267.5,"last":267.25,"open":266.51,"high":268.0,"low":265.9,"volume":9692354.0,"turnover":2590902011.0832,"feed":15,"ticker":"AAPL","num_trades":73740},{"date":"2019-11-27","bid":266.61,"ask":266.7,"last":267.84,"open":265.74,"high":267.98,"low":265.31,"volume":14636455.0,"turnover":3901418391.3949,"feed":15,"ticker":"AAPL","num_trades":118162},{"date":"2019-11-26","bid":264.73,"ask":264.8,"last":264.29,"open":266.94,"high":267.21,"low":262.5,"volume":20060118.0,"turnover":5325909837.1098,"feed":15,"ticker":"AAPL","num_trades":127694},{"date":"2019-11-25","bid":266.7,"ask":266.75,"last":266.37,"open":262.71,"high":266.44,"low":262.52,"volume":18234140.0,"turnover":4837583584.0585,"feed":15,"ticker":"AAPL","num_trades":127258},{"date":"2019-11-22","bid":261.75,"ask":261.79,"last":261.78,"open":262.59,"high":263.18,"low":260.84,"volume":13903679.0,"turnover":3642312271.5178,"feed":15,"ticker":"AAPL","num_trades":124907},{"date":"2019-11-21","bid":262.26,"ask":262.29,"last":262.01,"open":263.69,"high":264.005,"low":261.18,"volume":26284447.0,"turnover":6840854941.989,"feed":15,"ticker":"AAPL","num_trades":144713},{"date":"2019-11-20","bid":263.35,"ask":263.4,"last":263.19,"open":265.54,"high":266.08,"low":260.4,"volume":23958620.0,"turnover":5353452172.5232,"feed":15,"ticker":"AAPL","num_trades":181725},{"date":"2019-11-19","bid":265.7,"ask":265.8,"last":266.29,"open":267.96,"high":268.0,"low":265.3926,"volume":14949379.0,"turnover":3985242637.147,"feed":15,"ticker":"AAPL","num_trades":128077},{"date":"2019-11-18","bid":267.0,"ask":267.04,"last":267.1,"open":265.8,"high":267.43,"low":264.23,"volume":20090998.0,"turnover":4878390073.0,"feed":15,"ticker":"AAPL","num_trades":166998},{"date":"2019-11-15","bid":266.05,"ask":266.09,"last":265.76,"open":263.68,"high":265.78,"low":263.01,"volume":23537627.0,"turnover":6030387708.6132,"feed":15,"ticker":"AAPL","num_trades":173032},{"date":"2019-11-14","bid":262.65,"ask":262.74,"last":262.64,"open":263.75,"high":264.88,"low":262.1,"volume":18312235.0,"turnover":4823516203.7463,"feed":15,"ticker":"AAPL","num_trades":182694},{"date":"2019-11-13","bid":264.55,"ask":264.69,"last":264.47,"open":261.11,"high":264.78,"low":261.07,"volume":23277930.0,"turnover":6134414757.7863,"feed":15,"ticker":"AAPL","num_trades":194745},{"date":"2019-11-12","bid":261.7,"ask":261.79,"last":261.96,"open":261.55,"high":262.79,"low":260.92,"volume":21831678.0,"turnover":4764214062.4532,"feed":15,"ticker":"AAPL","num_trades":158988},{"date":"2019-11-11","bid":262.42,"ask":262.45,"last":262.2,"open":258.34,"high":262.4612,"low":258.3,"volume":19132614.0,"turnover":4793429846.5758,"feed":15,"ticker":"AAPL","num_trades":149870},{"date":"2019-11-08","bid":260.03,"ask":260.11,"last":260.14,"open":258.69,"high":260.44,"low":256.85,"volume":15450683.0,"turnover":4000294127.7974,"feed":15,"ticker":"AAPL","num_trades":132627},{"date":"2019-11-07","bid":259.3,"ask":259.49,"last":259.43,"open":258.74,"high":260.35,"low":258.11,"volume":35690122.0,"turnover":9257700212.806801,"feed":15,"ticker":"AAPL","num_trades":304635},{"date":"2019-11-06","bid":257.6,"ask":257.72,"last":257.24,"open":256.77,"high":257.49,"low":255.365,"volume":14814994.0,"turnover":3801534111.3972,"feed":15,"ticker":"AAPL","num_trades":143599},{"date":"2019-11-05","bid":256.6,"ask":256.7,"last":257.13,"open":257.07,"high":258.19,"low":256.32,"volume":17027152.0,"turnover":4383756828.2977,"feed":15,"ticker":"AAPL","num_trades":155712},{"date":"2019-11-04","bid":257.91,"ask":257.99,"last":257.5,"open":257.37,"high":257.845,"low":255.38,"volume":24379249.0,"turnover":5867281985.9361,"feed":15,"ticker":"AAPL","num_trades":197331},{"date":"2019-11-01","bid":256.1,"ask":256.15,"last":255.82,"open":249.54,"high":255.93,"low":249.16,"volume":37042092.0,"turnover":9374875264.477301,"feed":15,"ticker":"AAPL","num_trades":278917},{"date":"2019-10-31","bid":248.56,"ask":248.6,"last":248.76,"open":247.24,"high":249.17,"low":245.55,"volume":32171092.0,"turnover":7971493695.9599,"feed":15,"ticker":"AAPL","num_trades":271132},{"date":"2019-10-30","bid":248.15,"ask":248.19,"last":243.26,"open":244.8,"high":245.3,"low":241.21,"volume":67093423.0,"turnover":16287071436.212999,"feed":15,"ticker":"AAPL","num_trades":703723},{"date":"2019-10-29","bid":243.83,"ask":243.85,"last":243.29,"open":249.01,"high":249.75,"low":242.57,"volume":33297540.0,"turnover":8154764667.1905,"feed":15,"ticker":"AAPL","num_trades":277180},{"date":"2019-10-28","bid":249.15,"ask":249.25,"last":249.05,"open":247.42,"high":249.25,"low":246.72,"volume":23340205.0,"turnover":5795695320.6461,"feed":15,"ticker":"AAPL","num_trades":190294},{"date":"2019-10-25","bid":246.71,"ask":246.75,"last":246.58,"open":243.16,"high":246.73,"low":242.88,"volume":16945108.0,"turnover":4153565853.8772,"feed":15,"ticker":"AAPL","num_trades":142105},{"date":"2019-10-24","bid":243.29,"ask":243.4,"last":243.58,"open":244.51,"high":244.8,"low":241.805,"volume":16923596.0,"turnover":4113002214.8876,"feed":15,"ticker":"AAPL","num_trades":144120},{"date":"2019-10-23","bid":244.0,"ask":244.11,"last":243.18,"open":242.1,"high":243.24,"low":241.2201,"volume":18518458.0,"turnover":4489011642.6027,"feed":15,"ticker":"AAPL","num_trades":156054},{"date":"2019-10-22","bid":239.02,"ask":239.18,"last":239.96,"open":241.16,"high":242.2,"low":239.625,"volume":20091752.0,"turnover":4845021637.3826,"feed":15,"ticker":"AAPL","num_trades":179924},{"date":"2019-10-21","bid":240.6,"ask":240.7,"last":240.51,"open":237.52,"high":240.99,"low":237.32,"volume":22345010.0,"turnover":10208708493.702,"feed":15,"ticker":"AAPL","num_trades":387987},{"date":"2019-10-18","bid":236.21,"ask":236.25,"last":236.41,"open":234.59,"high":237.58,"low":234.29,"volume":23662790.0,"turnover":5580308435.9161,"feed":15,"ticker":"AAPL","num_trades":204279},{"date":"2019-10-17","bid":235.2,"ask":235.3,"last":235.28,"open":235.09,"high":236.15,"low":233.52,"volume":49617067.0,"turnover":11654767631.818001,"feed":15,"ticker":"AAPL","num_trades":535566},{"date":"2019-10-16","bid":234.3,"ask":234.67,"last":234.37,"open":233.37,"high":235.24,"low":233.2,"volume":17411379.0,"turnover":4077089036.182,"feed":15,"ticker":"AAPL","num_trades":194651},{"date":"2019-10-15","bid":235.0,"ask":235.08,"last":235.32,"open":236.39,"high":237.63,"low":234.88,"volume":19779316.0,"turnover":4670308526.7544,"feed":15,"ticker":"AAPL","num_trades":200808},{"date":"2019-10-14","bid":236.45,"ask":236.49,"last":235.87,"open":235.02,"high":238.1342,"low":234.6701,"volume":23697819.0,"turnover":5609233861.2922,"feed":15,"ticker":"AAPL","num_trades":218315},{"date":"2019-10-11","bid":237.15,"ask":237.25,"last":236.21,"open":232.995,"high":237.64,"low":232.3075,"volume":39777156.0,"turnover":9353214578.8487,"feed":15,"ticker":"AAPL","num_trades":382754},{"date":"2019-10-10","bid":231.18,"ask":231.24,"last":230.09,"open":227.95,"high":230.44,"low":227.3,"volume":27292554.0,"turnover":6266377891.4797,"feed":15,"ticker":"AAPL","num_trades":302119},{"date":"2019-10-09","bid":224.29,"ask":224.3,"last":227.03,"open":227.03,"high":227.79,"low":225.64,"volume":53231226.0,"turnover":12070804402.813,"feed":15,"ticker":"AAPL","num_trades":601409},{"date":"2019-10-08","bid":223.68,"ask":223.8,"last":224.4,"open":225.76,"high":228.06,"low":224.33,"volume":52876112.0,"turnover":11950362389.370001,"feed":15,"ticker":"AAPL","num_trades":675812},{"date":"2019-10-07","bid":227.33,"ask":227.44,"last":227.06,"open":226.27,"high":229.93,"low":225.84,"volume":58438761.0,"turnover":13332053763.724001,"feed":15,"ticker":"AAPL","num_trades":634399},{"date":"2019-10-04","bid":226.95,"ask":227.08,"last":227.01,"open":225.64,"high":227.49,"low":223.89,"volume":33719853.0,"turnover":7616235982.7612,"feed":15,"ticker":"AAPL","num_trades":309850},{"date":"2019-10-03","bid":220.36,"ask":220.53,"last":220.82,"open":218.43,"high":220.96,"low":215.132,"volume":82470070.0,"turnover":18046300824.819,"feed":15,"ticker":"AAPL","num_trades":1032947},{"date":"2019-10-02","bid":218.38,"ask":218.5,"last":218.96,"open":223.06,"high":223.58,"low":217.93,"volume":33451973.0,"turnover":7354081314.1867,"feed":15,"ticker":"AAPL","num_trades":442370},{"date":"2019-10-01","bid":225.1,"ask":225.2,"last":224.59,"open":225.08,"high":228.22,"low":224.2,"volume":84903691.0,"turnover":19178627715.841999,"feed":15,"ticker":"AAPL","num_trades":1061178},{"date":"2019-09-30","bid":224.52,"ask":224.53,"last":223.97,"open":220.9,"high":224.57,"low":220.79,"volume":24569724.0,"turnover":5481287901.751,"feed":15,"ticker":"AAPL","num_trades":276155},{"date":"2019-09-27","bid":218.62,"ask":218.89,"last":218.82,"open":220.54,"high":220.96,"low":217.2814,"volume":125814775.0,"turnover":27513910290.119999,"feed":15,"ticker":"AAPL","num_trades":1658111},{"date":"2019-09-26","bid":219.68,"ask":219.7,"last":219.89,"open":220.0,"high":220.94,"low":218.83,"volume":17863674.0,"turnover":3927813343.2687,"feed":15,"ticker":"AAPL","num_trades":229306},{"date":"2019-09-25","bid":220.82,"ask":220.86,"last":221.03,"open":218.58,"high":221.5,"low":217.1402,"volume":20944194.0,"turnover":4606137252.701,"feed":15,"ticker":"AAPL","num_trades":262834},{"date":"2019-09-24","bid":218.16,"ask":218.45,"last":217.68,"open":221.03,"high":222.49,"low":217.19,"volume":73901620.0,"turnover":16188034838.962,"feed":15,"ticker":"AAPL","num_trades":923431},{"date":"2019-09-23","bid":219.83,"ask":219.85,"last":218.72,"open":218.95,"high":219.84,"low":217.66,"volume":36274265.0,"turnover":7938531435.4849,"feed":15,"ticker":"AAPL","num_trades":417552},{"date":"2019-09-20","bid":217.65,"ask":217.74,"last":218.19,"open":221.39,"high":222.56,"low":217.475,"volume":56834730.0,"turnover":12513316292.228001,"feed":15,"ticker":"AAPL","num_trades":604367},{"date":"2019-09-19","bid":220.97,"ask":221.19,"last":220.96,"open":222.01,"high":223.76,"low":220.37,"volume":21276060.0,"turnover":4722169518.7381,"feed":15,"ticker":"AAPL","num_trades":195927},{"date":"2019-09-18","bid":222.35,"ask":222.47,"last":222.77,"open":221.12,"high":222.85,"low":219.44,"volume":70924535.0,"turnover":15716008482.737,"feed":15,"ticker":"AAPL","num_trades":624858},{"date":"2019-09-17","bid":220.8,"ask":221.0,"last":220.7,"open":219.96,"high":220.82,"low":219.12,"volume":17328355.0,"turnover":3813067892.5228,"feed":15,"ticker":"AAPL","num_trades":153007},{"date":"2019-09-16","bid":220.29,"ask":220.3,"last":219.9,"open":217.73,"high":220.13,"low":217.56,"volume":20396609.0,"turnover":4473568198.7011,"feed":15,"ticker":"AAPL","num_trades":237320},{"date":"2019-09-13","bid":218.45,"ask":218.52,"last":218.75,"open":220.0,"high":220.79,"low":217.02,"volume":74653296.0,"turnover":16339863820.149,"feed":15,"ticker":"AAPL","num_trades":947977},{"date":"2019-09-12","bid":223.35,"ask":223.4,"last":223.085,"open":224.8,"high":226.42,"low":222.86,"volume":62808684.0,"turnover":14107080020.528999,"feed":15,"ticker":"AAPL","num_trades":602344},{"date":"2019-09-11","bid":225.61,"ask":225.63,"last":223.59,"open":218.07,"high":223.71,"low":216.7,"volume":84978043.0,"turnover":18812601371.557999,"feed":15,"ticker":"AAPL","num_trades":821657},{"date":"2019-09-10","bid":216.8,"ask":216.94,"last":216.7,"open":213.86,"high":216.78,"low":211.71,"volume":53577098.0,"turnover":11488893029.344999,"feed":15,"ticker":"AAPL","num_trades":609374},{"date":"2019-09-09","bid":214.5,"ask":214.56,"last":214.17,"open":214.84,"high":216.44,"low":211.07,"volume":25825116.0,"turnover":5551356841.3533,"feed":15,"ticker":"AAPL","num_trades":297325},{"date":"2019-09-06","bid":213.62,"ask":213.7,"last":213.26,"open":214.05,"high":214.42,"low":212.51,"volume":37396398.0,"turnover":7978304205.4899,"feed":15,"ticker":"AAPL","num_trades":400472},{"date":"2019-09-05","bid":213.6,"ask":213.66,"last":213.28,"open":212.0,"high":213.97,"low":211.51,"volume":22312345.0,"turnover":4749280333.3464,"feed":15,"ticker":"AAPL","num_trades":198818},{"date":"2019-09-04","bid":209.01,"ask":209.08,"last":209.19,"open":208.39,"high":209.48,"low":207.31,"volume":18757385.0,"turnover":3912818139.1898,"feed":15,"ticker":"AAPL","num_trades":165189},{"date":"2019-09-03","bid":205.89,"ask":206.12,"last":205.7,"open":206.42,"high":206.98,"low":204.22,"volume":18726314.0,"turnover":3846479407.3483,"feed":15,"ticker":"AAPL","num_trades":164426},{"date":"2019-08-30","bid":208.0,"ask":208.15,"last":208.74,"open":210.16,"high":210.45,"low":207.2,"volume":18508983.0,"turnover":3857571761.6779,"feed":15,"ticker":"AAPL","num_trades":156718},{"date":"2019-08-29","bid":208.73,"ask":208.8,"last":209.01,"open":208.5,"high":209.32,"low":206.655,"volume":19894403.0,"turnover":4148381156.9388,"feed":15,"ticker":"AAPL","num_trades":163322},{"date":"2019-08-28","bid":205.2,"ask":205.25,"last":205.53,"open":204.1,"high":205.72,"low":203.32,"volume":14545825.0,"turnover":2980615264.6947,"feed":15,"ticker":"AAPL","num_trades":135927},{"date":"2019-08-27","bid":204.7,"ask":204.96,"last":204.16,"open":207.86,"high":208.55,"low":203.53,"volume":23742963.0,"turnover":4873173001.3552,"feed":15,"ticker":"AAPL","num_trades":179602},{"date":"2019-08-26","bid":206.13,"ask":206.49,"last":206.49,"open":205.86,"high":207.19,"low":205.0573,"volume":24858716.0,"turnover":5124938393.8501,"feed":15,"ticker":"AAPL","num_trades":196815},{"date":"2019-08-23","bid":201.6,"ask":201.8,"last":202.64,"open":209.43,"high":212.051,"low":201.0,"volume":163540819.0,"turnover":33512882899.608002,"feed":15,"ticker":"AAPL","num_trades":1417355},{"date":"2019-08-22","bid":212.36,"ask":212.37,"last":212.46,"open":213.19,"high":214.435,"low":210.75,"volume":21021323.0,"turnover":4470771160.2212,"feed":15,"ticker":"AAPL","num_trades":165110},{"date":"2019-08-21","bid":213.32,"ask":213.4,"last":212.64,"open":212.99,"high":213.65,"low":211.6032,"volume":20084905.0,"turnover":4275614188.424,"feed":15,"ticker":"AAPL","num_trades":167312},{"date":"2019-08-20","bid":210.5,"ask":210.69,"last":210.36,"open":210.78,"high":213.35,"low":210.32,"volume":22871501.0,"turnover":4841694059.622,"feed":15,"ticker":"AAPL","num_trades":173866},{"date":"2019-08-19","bid":210.05,"ask":210.1,"last":210.35,"open":210.62,"high":212.7307,"low":206.5,"volume":23240132.0,"turnover":4914910674.5572,"feed":15,"ticker":"AAPL","num_trades":180868},{"date":"2019-08-16","bid":206.4,"ask":206.5,"last":206.5,"open":204.02,"high":207.16,"low":203.84,"volume":26237452.0,"turnover":5401387020.035,"feed":15,"ticker":"AAPL","num_trades":216729},{"date":"2019-08-15","bid":202.5,"ask":202.54,"last":201.74,"open":203.46,"high":205.14,"low":199.67,"volume":26273484.0,"turnover":5309165489.93,"feed":15,"ticker":"AAPL","num_trades":243185},{"date":"2019-08-14","bid":202.37,"ask":202.4,"last":202.75,"open":203.15,"high":206.44,"low":202.5869,"volume":34222575.0,"turnover":6980547676.7036,"feed":15,"ticker":"AAPL","num_trades":287940},{"date":"2019-08-13","bid":209.51,"ask":209.6,"last":209.0,"open":201.02,"high":212.14,"low":200.48,"volume":45466134.0,"turnover":9485601947.6049,"feed":15,"ticker":"AAPL","num_trades":370017},{"date":"2019-08-12","bid":200.6,"ask":200.73,"last":200.48,"open":199.46,"high":202.0516,"low":199.15,"volume":21589196.0,"turnover":4335555178.7925,"feed":15,"ticker":"AAPL","num_trades":178588},{"date":"2019-08-09","bid":201.0,"ask":201.4,"last":200.99,"open":201.3,"high":202.76,"low":199.3,"volume":23394596.0,"turnover":4707541533.4345,"feed":15,"ticker":"AAPL","num_trades":189366},{"date":"2019-08-08","bid":203.07,"ask":203.15,"last":203.43,"open":200.2,"high":203.53,"low":199.39,"volume":25989632.0,"turnover":5246715713.3125,"feed":15,"ticker":"AAPL","num_trades":242648},{"date":"2019-08-07","bid":198.89,"ask":198.9,"last":199.04,"open":195.42,"high":199.56,"low":193.82,"volume":31674420.0,"turnover":6243810082.9218,"feed":15,"ticker":"AAPL","num_trades":267153},{"date":"2019-08-06","bid":196.05,"ask":196.47,"last":197.0,"open":196.31,"high":198.067,"low":194.04,"volume":34433502.0,"turnover":6758299740.4527,"feed":15,"ticker":"AAPL","num_trades":276972},{"date":"2019-08-05","bid":187.3,"ask":187.6,"last":193.19,"open":197.98,"high":198.649,"low":192.58,"volume":46894974.0,"turnover":9132926872.7535,"feed":15,"ticker":"AAPL","num_trades":456349},{"date":"2019-08-02","bid":204.4,"ask":204.6,"last":204.02,"open":205.53,"high":206.43,"low":201.63,"volume":142848015.0,"turnover":29121745651.73,"feed":15,"ticker":"AAPL","num_trades":1258205},{"date":"2019-08-01","bid":206.65,"ask":206.84,"last":208.26,"open":213.9,"high":218.03,"low":206.7435,"volume":95980611.0,"turnover":20358307967.726002,"feed":15,"ticker":"AAPL","num_trades":823771},{"date":"2019-07-31","bid":212.9,"ask":213.0,"last":213.04,"open":216.425,"high":221.37,"low":211.3,"volume":198609682.0,"turnover":43162611447.396004,"feed":15,"ticker":"AAPL","num_trades":1564384},{"date":"2019-07-30","bid":218.1,"ask":218.14,"last":208.86,"open":208.74,"high":210.16,"low":207.31,"volume":57205145.0,"turnover":11983633094.205999,"feed":15,"ticker":"AAPL","num_trades":519770},{"date":"2019-07-29","bid":209.68,"ask":209.7,"last":209.68,"open":208.46,"high":210.64,"low":208.44,"volume":40273856.0,"turnover":8453025901.55,"feed":15,"ticker":"AAPL","num_trades":342468},{"date":"2019-07-26","bid":207.75,"ask":207.79,"last":207.75,"open":207.48,"high":209.73,"low":207.14,"volume":96642941.0,"turnover":20123001615.119999,"feed":15,"ticker":"AAPL","num_trades":794162},{"date":"2019-07-25","bid":207.17,"ask":207.34,"last":207.02,"open":208.89,"high":209.23,"low":206.73,"volume":24865720.0,"turnover":5165544911.4689,"feed":15,"ticker":"AAPL","num_trades":231484},{"date":"2019-07-24","bid":209.0,"ask":209.04,"last":208.67,"open":207.67,"high":209.15,"low":207.17,"volume":28142109.0,"turnover":5859750841.368,"feed":15,"ticker":"AAPL","num_trades":227640},{"date":"2019-07-23","bid":207.95,"ask":207.96,"last":208.84,"open":208.46,"high":208.91,"low":207.29,"volume":64005419.0,"turnover":13319195038.433001,"feed":15,"ticker":"AAPL","num_trades":510612},{"date":"2019-07-22","bid":207.9,"ask":208.0,"last":207.22,"open":203.7,"high":207.23,"low":202.59,"volume":21169486.0,"turnover":4363775836.5557,"feed":15,"ticker":"AAPL","num_trades":164032},{"date":"2019-07-19","bid":202.35,"ask":202.55,"last":202.59,"open":205.79,"high":206.5,"low":202.36,"volume":19515765.0,"turnover":3988361887.0787,"feed":15,"ticker":"AAPL","num_trades":154637},{"date":"2019-07-18","bid":205.86,"ask":206.01,"last":205.66,"open":204.0,"high":205.88,"low":203.7,"volume":16684244.0,"turnover":3420712874.7,"feed":15,"ticker":"AAPL","num_trades":141801},{"date":"2019-07-17","bid":203.0,"ask":203.05,"last":203.35,"open":204.05,"high":205.0915,"low":203.27,"volume":12951976.0,"turnover":2645896304.5264,"feed":15,"ticker":"AAPL","num_trades":109062},{"date":"2019-07-16","bid":204.1,"ask":204.19,"last":204.5,"open":204.59,"high":206.11,"low":203.5,"volume":15509119.0,"turnover":3175636404.2448,"feed":15,"ticker":"AAPL","num_trades":137308},{"date":"2019-07-15","bid":205.15,"ask":205.19,"last":205.21,"open":204.09,"high":205.87,"low":204.0,"volume":15919341.0,"turnover":3263540061.909,"feed":15,"ticker":"AAPL","num_trades":138086},{"date":"2019-07-12","bid":203.23,"ask":203.31,"last":203.3,"open":202.45,"high":204.0,"low":202.2,"volume":17022685.0,"turnover":3462695088.3144,"feed":15,"ticker":"AAPL","num_trades":145195},{"date":"2019-07-11","bid":201.62,"ask":201.65,"last":201.75,"open":203.31,"high":204.39,"low":201.71,"volume":17803742.0,"turnover":3617932934.1723,"feed":15,"ticker":"AAPL","num_trades":154104},{"date":"2019-07-10","bid":203.3,"ask":203.31,"last":203.23,"open":201.85,"high":203.73,"low":201.56,"volume":17170197.0,"turnover":3486662645.2587,"feed":15,"ticker":"AAPL","num_trades":147779},{"date":"2019-07-09","bid":200.83,"ask":200.99,"last":201.24,"open":199.2,"high":201.51,"low":198.81,"volume":19158951.0,"turnover":3842788518.8282,"feed":15,"ticker":"AAPL","num_trades":169432},{"date":"2019-07-08","bid":200.2,"ask":200.48,"last":200.02,"open":200.81,"high":201.4,"low":198.41,"volume":24132247.0,"turnover":4820935026.0824,"feed":15,"ticker":"AAPL","num_trades":217259},{"date":"2019-07-05","bid":203.92,"ask":204.03,"last":204.23,"open":203.35,"high":205.08,"low":202.9,"volume":16640474.0,"turnover":3398599367.6841,"feed":15,"ticker":"AAPL","num_trades":160635},{"date":"2019-07-03","bid":204.3,"ask":204.4,"last":204.41,"open":203.28,"high":204.44,"low":202.6901,"volume":10826025.0,"turnover":2205455333.696,"feed":15,"ticker":"AAPL","num_trades":92854},{"date":"2019-07-02","bid":202.86,"ask":202.95,"last":202.73,"open":201.41,"high":203.1323,"low":201.36,"volume":16532716.0,"turnover":3344878769.5049,"feed":15,"ticker":"AAPL","num_trades":154619},{"date":"2019-07-01","bid":201.25,"ask":201.35,"last":201.55,"open":203.17,"high":204.49,"low":200.65,"volume":26124749.0,"turnover":5286716475.6974,"feed":15,"ticker":"AAPL","num_trades":235264},{"date":"2019-06-28","bid":197.99,"ask":198.3,"last":197.92,"open":198.68,"high":199.495,"low":197.05,"volume":27706541.0,"turnover":5485790828.993,"feed":15,"ticker":"AAPL","num_trades":180784},{"date":"2019-06-27","bid":198.35,"ask":198.4,"last":199.74,"open":200.4,"high":201.57,"low":199.57,"volume":17103872.0,"turnover":3426351099.2486,"feed":15,"ticker":"AAPL","num_trades":146592},{"date":"2019-06-26","bid":199.84,"ask":199.99,"last":199.8,"open":197.77,"high":200.99,"low":197.35,"volume":25488407.0,"turnover":5097354938.5189,"feed":15,"ticker":"AAPL","num_trades":203211},{"date":"2019-06-25","bid":195.62,"ask":195.75,"last":195.57,"open":198.57,"high":199.26,"low":195.29,"volume":20350461.0,"turnover":4012154221.7266,"feed":15,"ticker":"AAPL","num_trades":176058},{"date":"2019-06-24","bid":198.68,"ask":198.75,"last":198.58,"open":198.54,"high":200.16,"low":198.17,"volume":17491434.0,"turnover":3484449636.6294,"feed":15,"ticker":"AAPL","num_trades":132900},{"date":"2019-06-21","bid":198.04,"ask":198.15,"last":198.78,"open":198.5306,"high":200.85,"low":198.15,"volume":36811660.0,"turnover":7339225116.8369,"feed":15,"ticker":"AAPL","num_trades":180464},{"date":"2019-06-20","bid":199.2,"ask":199.3,"last":199.46,"open":200.37,"high":200.61,"low":198.04,"volume":20745216.0,"turnover":4134521044.367,"feed":15,"ticker":"AAPL","num_trades":167967},{"date":"2019-06-19","bid":198.37,"ask":198.4,"last":197.87,"open":199.7,"high":199.88,"low":197.31,"volume":20066668.0,"turnover":3979090791.2563,"feed":15,"ticker":"AAPL","num_trades":155040},{"date":"2019-06-18","bid":199.25,"ask":199.3,"last":198.45,"open":196.0,"high":200.29,"low":195.21,"volume":27972365.0,"turnover":5553755929.9379,"feed":15,"ticker":"AAPL","num_trades":228858},{"date":"2019-06-17","bid":194.05,"ask":194.14,"last":193.89,"open":192.9,"high":194.95,"low":192.17,"volume":13600217.0,"turnover":2640069245.6128,"feed":15,"ticker":"AAPL","num_trades":114439},{"date":"2019-06-14","bid":192.65,"ask":192.86,"last":192.74,"open":191.545,"high":193.5863,"low":190.3,"volume":17334048.0,"turnover":3330726069.296,"feed":15,"ticker":"AAPL","num_trades":143905},{"date":"2019-06-13","bid":192.65,"ask":192.76,"last":194.15,"open":194.7,"high":196.79,"low":193.6,"volume":19606167.0,"turnover":3826316807.3501,"feed":15,"ticker":"AAPL","num_trades":142539},{"date":"2019-06-12","bid":194.6,"ask":194.7,"last":194.19,"open":193.95,"high":195.97,"low":193.385,"volume":17258633.0,"turnover":3358691720.4413,"feed":15,"ticker":"AAPL","num_trades":129364},{"date":"2019-06-11","bid":194.22,"ask":194.49,"last":194.81,"open":194.86,"high":196.0,"low":193.6,"volume":24205515.0,"turnover":4711757737.4936,"feed":15,"ticker":"AAPL","num_trades":180234},{"date":"2019-06-10","bid":192.76,"ask":192.85,"last":192.58,"open":191.81,"high":195.37,"low":191.62,"volume":25349532.0,"turnover":4900753374.4818,"feed":15,"ticker":"AAPL","num_trades":198071},{"date":"2019-06-07","bid":190.25,"ask":190.35,"last":190.15,"open":186.51,"high":191.92,"low":185.77,"volume":29849146.0,"turnover":5664853944.3884,"feed":15,"ticker":"AAPL","num_trades":235376},{"date":"2019-06-06","bid":185.31,"ask":185.33,"last":185.22,"open":183.08,"high":185.47,"low":182.1489,"volume":19993607.0,"turnover":3675397234.6633,"feed":15,"ticker":"AAPL","num_trades":160009},{"date":"2019-06-05","bid":181.62,"ask":182.0,"last":182.54,"open":184.28,"high":184.99,"low":181.14,"volume":28384790.0,"turnover":5189915958.9322,"feed":15,"ticker":"AAPL","num_trades":235829},{"date":"2019-06-04","bid":181.5,"ask":181.55,"last":179.64,"open":175.44,"high":179.83,"low":174.52,"volume":29521933.0,"turnover":5256516276.3446,"feed":15,"ticker":"AAPL","num_trades":238904},{"date":"2019-06-03","bid":173.78,"ask":174.1,"last":173.3,"open":175.6,"high":177.92,"low":170.27,"volume":39156092.0,"turnover":6829644323.8704,"feed":15,"ticker":"AAPL","num_trades":305315},{"date":"2019-05-31","bid":174.82,"ask":174.93,"last":175.07,"open":176.23,"high":177.99,"low":174.99,"volume":25219209.0,"turnover":4449533431.5066,"feed":15,"ticker":"AAPL","num_trades":202744},{"date":"2019-05-30","bid":176.55,"ask":176.8,"last":178.3,"open":177.95,"high":179.23,"low":176.67,"volume":20597585.0,"turnover":3665679390.3144,"feed":15,"ticker":"AAPL","num_trades":165597},{"date":"2019-05-29","bid":177.46,"ask":177.59,"last":177.38,"open":176.42,"high":179.35,"low":176.0,"volume":27859191.0,"turnover":4946685801.2186,"feed":15,"ticker":"AAPL","num_trades":212143},{"date":"2019-05-28","bid":178.35,"ask":178.45,"last":178.23,"open":178.92,"high":180.59,"low":177.91,"volume":26403311.0,"turnover":4723695869.4358,"feed":15,"ticker":"AAPL","num_trades":189277},{"date":"2019-05-24","bid":178.29,"ask":178.34,"last":178.97,"open":180.3,"high":182.14,"low":178.62,"volume":22775475.0,"turnover":4103128820.5282,"feed":15,"ticker":"AAPL","num_trades":181882},{"date":"2019-05-23","bid":179.86,"ask":179.95,"last":179.66,"open":179.72,"high":180.54,"low":177.81,"volume":35556889.0,"turnover":6376376527.401,"feed":15,"ticker":"AAPL","num_trades":264305},{"date":"2019-05-22","bid":182.25,"ask":182.35,"last":182.78,"open":184.86,"high":185.71,"low":182.55,"volume":28961307.0,"turnover":5320353726.0179,"feed":15,"ticker":"AAPL","num_trades":210850},{"date":"2019-05-21","bid":186.81,"ask":186.95,"last":186.6,"open":185.22,"high":188.0,"low":184.7,"volume":26737665.0,"turnover":4993542551.3294,"feed":15,"ticker":"AAPL","num_trades":190531},{"date":"2019-05-20","bid":183.55,"ask":183.56,"last":183.09,"open":183.52,"high":184.349,"low":180.2839,"volume":70664573.0,"turnover":12909314520.235001,"feed":15,"ticker":"AAPL","num_trades":560867},{"date":"2019-05-17","bid":189.0,"ask":189.3,"last":189.0,"open":186.93,"high":190.9,"low":186.76,"volume":96048974.0,"turnover":18173411272.584999,"feed":15,"ticker":"AAPL","num_trades":689161},{"date":"2019-05-16","bid":190.0,"ask":190.08,"last":190.08,"open":189.91,"high":192.4689,"low":188.84,"volume":31680012.0,"turnover":6033376554.5734,"feed":15,"ticker":"AAPL","num_trades":227289},{"date":"2019-05-15","bid":190.65,"ask":190.75,"last":190.92,"open":186.27,"high":191.75,"low":186.02,"volume":117023001.0,"turnover":22215818145.327,"feed":15,"ticker":"AAPL","num_trades":1005553},{"date":"2019-05-14","bid":188.92,"ask":189.0,"last":188.66,"open":186.41,"high":189.7,"low":185.41,"volume":62312931.0,"turnover":11722375986.437,"feed":15,"ticker":"AAPL","num_trades":490629},{"date":"2019-05-13","bid":184.23,"ask":184.28,"last":185.72,"open":187.71,"high":189.47,"low":182.85,"volume":54588791.0,"turnover":10199230410.59,"feed":15,"ticker":"AAPL","num_trades":459780},{"date":"2019-05-10","bid":197.1,"ask":197.14,"last":197.18,"open":197.419,"high":198.85,"low":192.77,"volume":75563504.0,"turnover":14806269375.98,"feed":15,"ticker":"AAPL","num_trades":640563},{"date":"2019-05-09","bid":200.53,"ask":200.65,"last":200.72,"open":200.4,"high":201.68,"low":196.66,"volume":122399450.0,"turnover":24385546704.479,"feed":15,"ticker":"AAPL","num_trades":1059977},{"date":"2019-05-08","bid":203.02,"ask":203.1,"last":202.9,"open":201.9,"high":205.33,"low":201.75,"volume":47109625.0,"turnover":9597782034.4639,"feed":15,"ticker":"AAPL","num_trades":367102},{"date":"2019-05-07","bid":202.52,"ask":202.83,"last":202.86,"open":205.88,"high":207.4175,"low":200.825,"volume":37357282.0,"turnover":7605520835.5537,"feed":15,"ticker":"AAPL","num_trades":289099},{"date":"2019-05-06","bid":207.3,"ask":207.35,"last":208.48,"open":204.29,"high":208.83,"low":203.5,"volume":31777649.0,"turnover":6586750170.2903,"feed":15,"ticker":"AAPL","num_trades":236862},{"date":"2019-05-03","bid":211.88,"ask":211.95,"last":211.75,"open":210.74,"high":211.84,"low":210.23,"volume":20273421.0,"turnover":4280481932.5906,"feed":15,"ticker":"AAPL","num_trades":148419},{"date":"2019-05-02","bid":209.1,"ask":209.28,"last":209.15,"open":209.84,"high":212.65,"low":208.13,"volume":29533124.0,"turnover":6208681588.8257,"feed":15,"ticker":"AAPL","num_trades":232702},{"date":"2019-05-01","bid":210.65,"ask":210.73,"last":210.52,"open":209.88,"high":215.3039,"low":200.67,"volume":65123874.0,"turnover":13849197147.402,"feed":15,"ticker":"AAPL","num_trades":441182},{"date":"2019-04-30","bid":210.75,"ask":210.79,"last":200.67,"open":203.06,"high":204.61,"low":199.11,"volume":38172412.0,"turnover":7668296112.969,"feed":15,"ticker":"AAPL","num_trades":331973},{"date":"2019-04-29","bid":203.12,"ask":203.25,"last":204.61,"open":204.4,"high":205.97,"low":203.86,"volume":20801815.0,"turnover":4263949510.1363,"feed":15,"ticker":"AAPL","num_trades":139033},{"date":"2019-04-26","bid":204.18,"ask":204.38,"last":204.3,"open":204.9,"high":205.0,"low":202.12,"volume":18241642.0,"turnover":3723073310.1001,"feed":15,"ticker":"AAPL","num_trades":140772},{"date":"2019-04-25","bid":205.0,"ask":205.19,"last":205.28,"open":206.83,"high":207.76,"low":205.1202,"volume":17166873.0,"turnover":3538206140.221,"feed":15,"ticker":"AAPL","num_trades":146394},{"date":"2019-04-24","bid":208.0,"ask":208.04,"last":207.16,"open":207.36,"high":208.48,"low":207.05,"volume":17540609.0,"turnover":3440994959.6109,"feed":15,"ticker":"AAPL","num_trades":124458},{"date":"2019-04-23","bid":207.56,"ask":207.59,"last":207.48,"open":204.43,"high":207.75,"low":203.9,"volume":22571371.0,"turnover":4660372398.0953,"feed":15,"ticker":"AAPL","num_trades":165078},{"date":"2019-04-22","bid":204.53,"ask":204.6,"last":204.53,"open":202.83,"high":204.94,"low":202.34,"volume":17021166.0,"turnover":3475979646.034,"feed":15,"ticker":"AAPL","num_trades":115755},{"date":"2019-04-18","bid":203.78,"ask":203.83,"last":203.86,"open":203.2,"high":204.15,"low":202.52,"volume":23721321.0,"turnover":4826851746.0658,"feed":15,"ticker":"AAPL","num_trades":144952},{"date":"2019-04-17","bid":203.0,"ask":203.1,"last":203.13,"open":199.54,"high":203.38,"low":198.61,"volume":28985814.0,"turnover":5850932067.6744,"feed":15,"ticker":"AAPL","num_trades":206884},{"date":"2019-04-16","bid":198.7,"ask":198.73,"last":199.25,"open":199.46,"high":201.37,"low":198.56,"volume":25295671.0,"turnover":5057174948.7222,"feed":15,"ticker":"AAPL","num_trades":201295},{"date":"2019-04-15","bid":199.26,"ask":199.28,"last":199.23,"open":198.58,"high":199.85,"low":198.01,"volume":16375726.0,"turnover":3258536552.2276,"feed":15,"ticker":"AAPL","num_trades":140240},{"date":"2019-04-12","bid":198.91,"ask":198.99,"last":198.87,"open":199.2,"high":200.14,"low":196.21,"volume":26930640.0,"turnover":5341212661.8442,"feed":15,"ticker":"AAPL","num_trades":195066},{"date":"2019-04-11","bid":198.8,"ask":198.85,"last":198.95,"open":200.85,"high":201.0,"low":198.4431,"volume":19488879.0,"turnover":3893207895.0828,"feed":15,"ticker":"AAPL","num_trades":142264},{"date":"2019-04-10","bid":200.78,"ask":200.85,"last":200.62,"open":198.68,"high":200.74,"low":198.18,"volume":21248143.0,"turnover":4238968369.9959,"feed":15,"ticker":"AAPL","num_trades":160715},{"date":"2019-04-09","bid":199.1,"ask":199.23,"last":199.5,"open":200.32,"high":202.85,"low":199.23,"volume":35087209.0,"turnover":7049726142.299,"feed":15,"ticker":"AAPL","num_trades":232043},{"date":"2019-04-08","bid":200.58,"ask":200.59,"last":200.1,"open":196.42,"high":200.23,"low":196.35,"volume":24756994.0,"turnover":4926177733.9339,"feed":15,"ticker":"AAPL","num_trades":180786},{"date":"2019-04-05","bid":196.89,"ask":197.0,"last":197.0,"open":196.47,"high":197.1,"low":195.93,"volume":17205818.0,"turnover":3383237813.534,"feed":15,"ticker":"AAPL","num_trades":123736},{"date":"2019-04-04","bid":195.55,"ask":195.58,"last":195.69,"open":194.8,"high":196.37,"low":193.14,"volume":18858305.0,"turnover":3690146261.56,"feed":15,"ticker":"AAPL","num_trades":134054},{"date":"2019-04-03","bid":195.5,"ask":195.58,"last":195.35,"open":193.25,"high":196.5,"low":193.15,"volume":22005568.0,"turnover":4297529020.6286,"feed":15,"ticker":"AAPL","num_trades":164209},{"date":"2019-04-02","bid":193.52,"ask":193.68,"last":194.02,"open":191.14,"high":194.46,"low":191.05,"volume":21122091.0,"turnover":4078367609.1791,"feed":15,"ticker":"AAPL","num_trades":169421},{"date":"2019-04-01","bid":191.4,"ask":191.5,"last":191.24,"open":191.63,"high":191.68,"low":188.38,"volume":25582836.0,"turnover":4868061140.6223,"feed":15,"ticker":"AAPL","num_trades":179977},{"date":"2019-03-29","bid":190.06,"ask":190.15,"last":189.95,"open":189.83,"high":190.08,"low":188.54,"volume":88370231.0,"turnover":16747794498.08,"feed":15,"ticker":"AAPL","num_trades":593309},{"date":"2019-03-28","bid":189.29,"ask":189.45,"last":188.72,"open":188.95,"high":189.559,"low":187.53,"volume":20338703.0,"turnover":3831997193.2402,"feed":15,"ticker":"AAPL","num_trades":151896},{"date":"2019-03-27","bid":188.1,"ask":188.18,"last":188.47,"open":188.75,"high":189.76,"low":186.55,"volume":29160092.0,"turnover":5496951936.1681,"feed":15,"ticker":"AAPL","num_trades":195157},{"date":"2019-03-26","bid":187.85,"ask":188.0,"last":186.79,"open":191.664,"high":192.88,"low":184.58,"volume":48404510.0,"turnover":9170316585.4611,"feed":15,"ticker":"AAPL","num_trades":343834},{"date":"2019-03-25","bid":188.9,"ask":189.16,"last":188.74,"open":191.51,"high":191.98,"low":186.6,"volume":42859427.0,"turnover":8095372215.4408,"feed":15,"ticker":"AAPL","num_trades":308427},{"date":"2019-03-22","bid":190.98,"ask":191.0,"last":191.05,"open":195.34,"high":197.69,"low":190.77,"volume":41221826.0,"turnover":7994682922.8897,"feed":15,"ticker":"AAPL","num_trades":298141},{"date":"2019-03-21","bid":195.98,"ask":195.99,"last":195.09,"open":190.02,"high":196.33,"low":188.16,"volume":49010742.0,"turnover":9521683830.000401,"feed":15,"ticker":"AAPL","num_trades":308018},{"date":"2019-03-20","bid":188.49,"ask":188.5,"last":188.16,"open":186.23,"high":189.49,"low":184.73,"volume":29800314.0,"turnover":5583214281.6601,"feed":15,"ticker":"AAPL","num_trades":192634},{"date":"2019-03-19","bid":186.0,"ask":186.09,"last":186.53,"open":188.35,"high":188.99,"low":185.92,"volume":30269269.0,"turnover":5673070253.4358,"feed":15,"ticker":"AAPL","num_trades":195108},{"date":"2019-03-18","bid":188.35,"ask":188.4,"last":188.02,"open":185.83,"high":188.39,"low":185.79,"volume":24779215.0,"turnover":4649605398.0976,"feed":15,"ticker":"AAPL","num_trades":163181},{"date":"2019-03-15","bid":185.85,"ask":185.88,"last":186.12,"open":184.85,"high":187.32,"low":183.73,"volume":68434606.0,"turnover":12723971454.846001,"feed":15,"ticker":"AAPL","num_trades":398303},{"date":"2019-03-14","bid":184.0,"ask":184.1,"last":183.73,"open":183.91,"high":184.1,"low":182.56,"volume":48237134.0,"turnover":8857472918.950899,"feed":15,"ticker":"AAPL","num_trades":344765},{"date":"2019-03-13","bid":182.46,"ask":182.54,"last":181.71,"open":182.25,"high":183.3,"low":180.92,"volume":52701143.0,"turnover":9590748563.879801,"feed":15,"ticker":"AAPL","num_trades":366968},{"date":"2019-03-12","bid":180.91,"ask":181.02,"last":180.91,"open":180.0,"high":182.67,"low":179.37,"volume":30034631.0,"turnover":5440355301.547,"feed":15,"ticker":"AAPL","num_trades":214405},{"date":"2019-03-11","bid":179.79,"ask":179.84,"last":178.9,"open":175.55,"high":179.13,"low":175.35,"volume":30959830.0,"turnover":5515734978.0857,"feed":15,"ticker":"AAPL","num_trades":210448},{"date":"2019-03-08","bid":173.02,"ask":173.1,"last":172.91,"open":170.32,"high":173.07,"low":169.5,"volume":22801124.0,"turnover":3917000732.1786,"feed":15,"ticker":"AAPL","num_trades":166637},{"date":"2019-03-07","bid":172.4,"ask":172.76,"last":172.5,"open":173.87,"high":174.44,"low":172.02,"volume":23080547.0,"turnover":3994999474.9906,"feed":15,"ticker":"AAPL","num_trades":178092},{"date":"2019-03-06","bid":174.18,"ask":174.25,"last":174.52,"open":174.67,"high":175.49,"low":173.94,"volume":19648901.0,"turnover":3433777660.0751,"feed":15,"ticker":"AAPL","num_trades":137402},{"date":"2019-03-05","bid":175.11,"ask":175.24,"last":175.53,"open":175.93,"high":175.9564,"low":174.54,"volume":15942685.0,"turnover":2796159322.2243,"feed":15,"ticker":"AAPL","num_trades":110731},{"date":"2019-03-04","bid":175.51,"ask":175.79,"last":175.85,"open":175.69,"high":177.75,"low":173.97,"volume":25781786.0,"turnover":4536654690.1394,"feed":15,"ticker":"AAPL","num_trades":189711},{"date":"2019-03-01","bid":175.06,"ask":175.12,"last":174.97,"open":174.28,"high":175.15,"low":172.89,"volume":24352767.0,"turnover":4243157760.6555,"feed":15,"ticker":"AAPL","num_trades":146096},{"date":"2019-02-28","bid":173.33,"ask":173.46,"last":173.15,"open":174.32,"high":174.91,"low":172.92,"volume":24116580.0,"turnover":4192473188.6478,"feed":15,"ticker":"AAPL","num_trades":123871},{"date":"2019-02-27","bid":174.67,"ask":174.77,"last":174.87,"open":173.23,"high":175.0,"low":172.73,"volume":47294246.0,"turnover":8228274630.2669,"feed":15,"ticker":"AAPL","num_trades":223465},{"date":"2019-02-26","bid":174.21,"ask":174.27,"last":174.33,"open":173.71,"high":175.3,"low":173.1732,"volume":17070211.0,"turnover":2824400991.1249,"feed":15,"ticker":"AAPL","num_trades":118044},{"date":"2019-02-25","bid":173.54,"ask":173.6,"last":174.23,"open":174.16,"high":175.87,"low":173.95,"volume":21029471.0,"turnover":3677600975.5335,"feed":15,"ticker":"AAPL","num_trades":156847},{"date":"2019-02-22","bid":172.76,"ask":172.8,"last":172.97,"open":171.58,"high":173.0,"low":171.38,"volume":17970344.0,"turnover":3097056895.6457,"feed":15,"ticker":"AAPL","num_trades":122985},{"date":"2019-02-21","bid":170.91,"ask":170.99,"last":171.06,"open":171.8,"high":172.37,"low":170.3,"volume":16691280.0,"turnover":2856499985.7548,"feed":15,"ticker":"AAPL","num_trades":136171},{"date":"2019-02-20","bid":171.77,"ask":171.88,"last":172.03,"open":171.19,"high":173.32,"low":170.99,"volume":24037175.0,"turnover":4141211875.7765,"feed":15,"ticker":"AAPL","num_trades":160626},{"date":"2019-02-19","bid":171.0,"ask":171.05,"last":170.93,"open":169.71,"high":171.44,"low":169.43,"volume":17816797.0,"turnover":3037990589.5456,"feed":15,"ticker":"AAPL","num_trades":130187},{"date":"2019-02-15","bid":170.43,"ask":170.5,"last":170.42,"open":171.25,"high":171.7,"low":169.75,"volume":17814863.0,"turnover":3035343449.1396,"feed":15,"ticker":"AAPL","num_trades":131524},{"date":"2019-02-14","bid":169.57,"ask":169.8,"last":170.79,"open":169.71,"high":171.2615,"low":169.38,"volume":16265017.0,"turnover":2776418316.7523,"feed":15,"ticker":"AAPL","num_trades":124681},{"date":"2019-02-13","bid":169.52,"ask":169.8,"last":170.18,"open":171.39,"high":172.48,"low":169.92,"volume":21398244.0,"turnover":3659354864.4344,"feed":15,"ticker":"AAPL","num_trades":149681},{"date":"2019-02-12","bid":171.45,"ask":171.5,"last":170.89,"open":170.1,"high":171.0,"low":169.7,"volume":22283523.0,"turnover":3663664414.4076,"feed":15,"ticker":"AAPL","num_trades":144184},{"date":"2019-02-11","bid":169.39,"ask":169.45,"last":169.43,"open":171.1,"high":171.21,"low":169.25,"volume":20083209.0,"turnover":3413610503.1503,"feed":15,"ticker":"AAPL","num_trades":144354},{"date":"2019-02-08","bid":170.3,"ask":170.37,"last":170.41,"open":168.83,"high":170.66,"low":168.42,"volume":19428833.0,"turnover":3300040082.319,"feed":15,"ticker":"AAPL","num_trades":134393},{"date":"2019-02-07","bid":170.6,"ask":170.74,"last":170.94,"open":172.4,"high":173.94,"low":170.34,"volume":30455153.0,"turnover":5227933106.6061,"feed":15,"ticker":"AAPL","num_trades":207675},{"date":"2019-02-06","bid":174.0,"ask":174.05,"last":174.24,"open":174.65,"high":175.57,"low":172.8531,"volume":27432468.0,"turnover":4780409209.1052,"feed":15,"ticker":"AAPL","num_trades":167482},{"date":"2019-02-05","bid":174.13,"ask":174.24,"last":174.18,"open":172.91,"high":175.08,"low":172.3501,"volume":28296000.0,"turnover":4923344372.8916,"feed":15,"ticker":"AAPL","num_trades":187994},{"date":"2019-02-04","bid":170.9,"ask":171.0,"last":171.25,"open":167.41,"high":171.655,"low":167.28,"volume":29744108.0,"turnover":5068278182.6387,"feed":15,"ticker":"AAPL","num_trades":200537},{"date":"2019-02-01","bid":166.52,"ask":166.55,"last":166.52,"open":166.93,"high":168.98,"low":165.93,"volume":30472426.0,"turnover":5094739973.7136,"feed":15,"ticker":"AAPL","num_trades":187744},{"date":"2019-01-31","bid":166.8,"ask":166.97,"last":166.44,"open":166.11,"high":169.0,"low":164.56,"volume":37738222.0,"turnover":6306880268.827,"feed":15,"ticker":"AAPL","num_trades":236978},{"date":"2019-01-30","bid":165.45,"ask":165.55,"last":165.25,"open":163.25,"high":166.15,"low":160.23,"volume":59812278.0,"turnover":9761643210.031099,"feed":15,"ticker":"AAPL","num_trades":382958},{"date":"2019-01-29","bid":163.5,"ask":163.54,"last":154.68,"open":156.25,"high":158.13,"low":154.11,"volume":30041248.0,"turnover":4678853338.3301,"feed":15,"ticker":"AAPL","num_trades":264711},{"date":"2019-01-28","bid":155.51,"ask":155.6,"last":156.3,"open":155.79,"high":156.33,"low":153.66,"volume":26177748.0,"turnover":3777202108.2479,"feed":15,"ticker":"AAPL","num_trades":176025},{"date":"2019-01-25","bid":157.82,"ask":157.91,"last":157.76,"open":155.48,"high":158.13,"low":154.32,"volume":32628428.0,"turnover":5117056203.3898,"feed":15,"ticker":"AAPL","num_trades":217134},{"date":"2019-01-24","bid":152.37,"ask":152.6,"last":152.7,"open":154.11,"high":154.48,"low":151.74,"volume":23228065.0,"turnover":3546486902.514,"feed":15,"ticker":"AAPL","num_trades":171579},{"date":"2019-01-23","bid":153.75,"ask":153.96,"last":153.92,"open":154.15,"high":155.14,"low":151.7,"volume":22367187.0,"turnover":3431576611.6169,"feed":15,"ticker":"AAPL","num_trades":153813},{"date":"2019-01-22","bid":153.49,"ask":153.5,"last":153.3,"open":156.41,"high":156.73,"low":152.62,"volume":77111301.0,"turnover":11893701832.264999,"feed":15,"ticker":"AAPL","num_trades":576765},{"date":"2019-01-18","bid":156.45,"ask":156.7,"last":156.82,"open":157.5,"high":157.88,"low":155.9806,"volume":32095735.0,"turnover":5037102461.7352,"feed":15,"ticker":"AAPL","num_trades":194705},{"date":"2019-01-17","bid":155.95,"ask":156.23,"last":155.86,"open":154.2,"high":157.66,"low":153.27,"volume":23492146.0,"turnover":3638181620.4758,"feed":15,"ticker":"AAPL","num_trades":162305},{"date":"2019-01-16","bid":154.35,"ask":154.6,"last":154.94,"open":153.01,"high":155.88,"low":153.0,"volume":24745851.0,"turnover":3835152669.5972,"feed":15,"ticker":"AAPL","num_trades":165321},{"date":"2019-01-15","bid":153.07,"ask":153.1,"last":153.07,"open":150.27,"high":153.39,"low":150.05,"volume":53754046.0,"turnover":8190101299.6062,"feed":15,"ticker":"AAPL","num_trades":340389},{"date":"2019-01-14","bid":150.27,"ask":150.29,"last":150.0,"open":150.85,"high":152.29,"low":149.22,"volume":30358183.0,"turnover":4554277866.0472,"feed":15,"ticker":"AAPL","num_trades":200268},{"date":"2019-01-11","bid":152.33,"ask":152.36,"last":152.29,"open":152.81,"high":153.7,"low":151.51,"volume":25455468.0,"turnover":3879438573.0431,"feed":15,"ticker":"AAPL","num_trades":173216},{"date":"2019-01-10","bid":154.24,"ask":154.25,"last":153.8,"open":152.5,"high":153.97,"low":150.86,"volume":35538836.0,"turnover":5426900365.5062,"feed":15,"ticker":"AAPL","num_trades":200482},{"date":"2019-01-09","bid":152.68,"ask":152.69,"last":153.31,"open":151.37,"high":154.53,"low":149.63,"volume":35986731.0,"turnover":5506843424.3271,"feed":15,"ticker":"AAPL","num_trades":250880},{"date":"2019-01-08","bid":151.0,"ask":151.15,"last":150.75,"open":149.35,"high":151.82,"low":148.52,"volume":65843645.0,"turnover":9895055603.388399,"feed":15,"ticker":"AAPL","num_trades":452550},{"date":"2019-01-07","bid":148.06,"ask":148.13,"last":147.93,"open":148.7,"high":148.8202,"low":145.9,"volume":96696394.0,"turnover":14248695069.934,"feed":15,"ticker":"AAPL","num_trades":622703},{"date":"2019-01-04","bid":148.21,"ask":148.4,"last":148.26,"open":144.53,"high":148.5499,"low":143.8,"volume":97443063.0,"turnover":14334727719.612,"feed":15,"ticker":"AAPL","num_trades":649503},{"date":"2019-01-03","bid":142.11,"ask":142.19,"last":142.085,"open":143.98,"high":157.92,"low":142.0,"volume":87249263.0,"turnover":12532873963.908001,"feed":15,"ticker":"AAPL","num_trades":662090},{"date":"2019-01-02","bid":145.98,"ask":146.0,"last":157.92,"open":154.89,"high":158.85,"low":154.23,"volume":30790018.0,"turnover":4832498513.7803,"feed":15,"ticker":"AAPL","num_trades":249082}]}}